Workbook

Sheet Assumptions
A1: Name | B1: Value | C1: Notes
A2: VAT_rate | B2: 0.23 | C2: Standard VAT rate (IE)
A3: Passives_overhead | B3: 0.05 | C3: Passives, connectors, headers as a % of active IC €
A4: PCBA_setup_eur | B4: 6.85 | C4: Assembly setup (converted to EUR)
A5: PCBA_stencil_eur | B5: 20 | C5: Stencil (converted to EUR)
A6: PCBA_Assembly_eur | B6: 30
A7: Digipot_channels_per_chip | B7: 2 | C7: TPL0102 dual channels per chip
A8: TMUX_per_channels | B8: 8 | C8: One TMUX1108 per 8 channels
A9: ADG2128_per_channels | B9: 96 | C9: One ADG2128 crosspoint per 96 channels
A10: Assembly_per_component_eur | B10: 0.005

Sheet PriceBook
A1: Part | B1: Price_1 | C1: Price_10 | D1: Price_100 | E1: Pins | F1: Notes
A2: TPL0102 | B2: 2.52 | C2: 1.87 | D2: 1.54 | E2: 14 | F2: Dual 256-tap digipot
A3: AD5160 | B3: 2.55 | C3: 2.1 | D3: 1.82 | E3: 8 | F3: Single 256-tap digipot, alt on small rails
A4: TMUX1108 | B4: 2.86 | C4: 2.45 | D4: 2.1 | E4: 16 | F4: 8:1 precision mux
A5: ADG2128 | B5: 13.87 | C5: 9.2 | D5: 7.74 | E5: 32 | F5: 8×12 crosspoint
A6: OPA140 | B6: 3.69 | C6: 2.8 | D6: 2.5 | E6: 8 | F6: JFET op-amp per neuron
A7: MCP6561 | B7: 0.473 | C7: 0.42 | D7: 0.39 | E7: 5 | F7: Low-power comparator per neuron
A8: TLV3501 | B8: 3.51 | C8: 2.9 | D8: 2.6 | E8: 6 | F8: Fast comparator, shared
A9: ADS1115 | B9: 5.41 | C9: 5.1 | D9: 4.8 | E9: 10 | F9: Low-cost ADC for small tiers
A10: ADS1263 | B10: 19.82 | C10: 18.5 | D10: 17 | E10: 28 | F10: Precision ADC for mid+ tiers
A11: ADR4550 | B11: 7.49 | C11: 6.8 | D11: 6.3 | E11: 8 | F11: 5 V reference
A12: LT3042 | B12: 7.82 | C12: 7.2 | D12: 6.7 | E12: 10 | F12: Low-noise LDO
A13: PICO2 | B13: 4.33 | C13: 4.1 | D13: 3.9 | E13: 0 | F13: Dev board, buy-in
A14: NUCLEO_U575 | B14: 20.7 | C14: 19.5 | D14: 18 | E14: 0 | F14: Dev board, buy-in

Sheet Tiers
A1: Tier | B1: Temporal? | C1: Rank | D1: ImgH | E1: ImgW | F1: Outputs | G1: Hidden | H1: Synapses | I1: Digipot chips | J1: TMUX1108 | K1: MUX | L1: Neurons | M1: ADC choice | N1: ADC unit € | O1: MCU choice | P1: MCU unit € | Q1: OPA140 qty | R1: OPA140 unit € | S1: OPA140 € | T1: MCP6561 qty | U1: MCP6561 unit € | V1: MCP6561 € | W1: TLV3501 qty | X1: TLV3501 unit € | Y1: TLV3501 € | Z1: Digipot unit € | AA1: Digipot € | AB1: TMUX unit € | AC1: TMUX € | AD1: MUX unit € | AE1: ADG2128 € | AF1: ADR4550 qty | AG1: ADR4550 unit € | AH1: ADR4550 € | AI1: LT3042 qty | AJ1: LT3042 unit € | AK1: LT3042 € | AL1: ADC € | AM1: MCU € | AN1: Active parts € ex VAT | AO1: Passives € ex VAT | AP1: Pins/joints est | AQ1: PCBA € ex VAT | AR1: Total € ex VAT | AS1: VAT € | AT1: Total € inc VAT | AU1: Funding bucket €
A2: POC | B2: No | C2: 1 | D2: 1 | E2: 1 | F2: 1 | G2: 0 | H2: =IF(B2="Yes", C2*(D2+E2)*IF(G2>0, G2, F2) + IF(G2>0, G2*F2, 0), D2*E2*IF(G2>0, G2, F2) + IF(G2>0, G2*F2, 0)) -> 1 | I2: =H2 -> 1 | J2: 0 | K2: =CEILING(H2/Assumptions!$B$8,1) -> 1 | L2: =F2+G2 -> 1 | M2: =IF(LEFT(A2,4)="€100","ADS1115",IF(LEFT(A2,4)="€250","ADS1115","ADS1263")) -> ADS1263 | N2: =INDEX(PriceBook!$B:$B, MATCH(M2, PriceBook!$A:$A, 0)) -> 19.82 | O2: =IF(LEFT(A2,4)="€100","PICO2",IF(LEFT(A2,4)="€250","PICO2","NUCLEO_U575")) -> NUCLEO_U575 | P2: =INDEX(PriceBook!$B:$B, MATCH(O2, PriceBook!$A:$A, 0)) -> 20.7 | Q2: =L2 -> 1 | R2: =IF(Q2>=100, INDEX(PriceBook!$D:$D, MATCH("OPA140", PriceBook!$A:$A, 0)), IF(Q2>=10, INDEX(PriceBook!$C:$C, MATCH("OPA140", PriceBook!$A:$A, 0)), INDEX(PriceBook!$B:$B, MATCH("OPA140", PriceBook!$A:$A, 0)))) -> 3.69 | S2: =Q2*R2 -> 3.69 | T2: =L2 -> 1 | U2: =INDEX(PriceBook!$B:$B, MATCH("MCP6561", PriceBook!$A:$A, 0)) -> 0.473 | V2: =T2*U2 -> 0.473 | W2: =IF(L2>0,1,0) -> 1 | X2: =INDEX(PriceBook!$B:$B, MATCH("TLV3501", PriceBook!$A:$A, 0)) -> 3.51 | Y2: =W2*X2 -> 3.51 | Z2: =IF(I2>=100, INDEX(PriceBook!$D:$D, MATCH("TPL0102", PriceBook!$A:$A, 0)), IF(I2>=10, INDEX(PriceBook!$C:$C, MATCH("TPL0102", PriceBook!$A:$A, 0)), INDEX(PriceBook!$B:$B, MATCH("TPL0102", PriceBook!$A:$A, 0)))) -> 2.52 | AA2: =I2*Z2 -> 2.52 | AB2: =INDEX(PriceBook!$B:$B, MATCH("TMUX1108", PriceBook!$A:$A, 0)) -> 2.86 | AC2: =J2*AB2 -> 0 | AD2: 4 | AE2: =K2*AD2 -> 4 | AF2: =IF(L2>=5,1,0) -> 0 | AG2: =INDEX(PriceBook!$B:$B, MATCH("ADR4550", PriceBook!$A:$A, 0)) -> 7.49 | AH2: =AF2*AG2 -> 0 | AI2: =IF(L2>=5,1,0) -> 0 | AJ2: =INDEX(PriceBook!$B:$B, MATCH("LT3042", PriceBook!$A:$A, 0)) -> 7.82 | AK2: =AI2*AJ2 -> 0 | AL2: =N2 -> 19.82 | AM2: =P2 -> 20.7 | AN2: =S2+V2+Y2+AA2+AC2+AE2+AH2+AK2+AL2+AM2 -> 54.713 | AO2: =AN2*Assumptions!$B$2 -> 12.58399 | AP2: =I2*INDEX(PriceBook!$E:$E, MATCH("TPL0102", PriceBook!$A:$A, 0))+J2*INDEX(PriceBook!$E:$E, MATCH("TMUX1108", PriceBook!$A:$A, 0))+K2*INDEX(PriceBook!$E:$E, MATCH("ADG2128", PriceBook!$A:$A, 0))+L2*INDEX(PriceBook!$E:$E, MATCH("OPA140", PriceBook!$A:$A, 0))+L2*INDEX(PriceBook!$E:$E, MATCH("MCP6561", PriceBook!$A:$A, 0))+IF(L2>0, INDEX(PriceBook!$E:$E, MATCH("TLV3501", PriceBook!$A:$A, 0)), 0)+INDEX(PriceBook!$E:$E, MATCH(M2, PriceBook!$A:$A, 0))+IF(L2>=5, INDEX(PriceBook!$E:$E, MATCH("ADR4550", PriceBook!$A:$A, 0)), 0)+IF(L2>=5, INDEX(PriceBook!$E:$E, MATCH("LT3042", PriceBook!$A:$A, 0)), 0) -> 93 | AQ2: =Assumptions!$B$6+Assumptions!$B$10*SUM(Tiers!C2:L2) -> 30.04 | AR2: =AN2+AO2+AQ2 -> 97.33699 | AS2: =AR2*Assumptions!$B$2 -> 22.387508 | AT2: =AR2+AS2 -> 119.7245 | AU2: =IF(AT2<=2000, CEILING(AT2, 250), CEILING(AT2, 500)) -> 250
A3: POC | B3: Yes | C3: 1 | D3: 1 | E3: 1 | F3: 1 | G3: 0 | H3: =IF(B3="Yes", C3*(D3+E3)*IF(G3>0, G3, F3) + IF(G3>0, G3*F3, 0), D3*E3*IF(G3>0, G3, F3) + IF(G3>0, G3*F3, 0)) -> 2 | I3: =H3 -> 2 | J3: 0 | K3: =CEILING(H3/Assumptions!$B$8,1) -> 1 | L3: =F3+G3 -> 1 | M3: =IF(LEFT(A3,4)="€100","ADS1115",IF(LEFT(A3,4)="€250","ADS1115","ADS1263")) -> ADS1263 | N3: =INDEX(PriceBook!$B:$B, MATCH(M3, PriceBook!$A:$A, 0)) -> 19.82 | O3: =IF(LEFT(A3,4)="€100","PICO2",IF(LEFT(A3,4)="€250","PICO2","NUCLEO_U575")) -> NUCLEO_U575 | P3: =INDEX(PriceBook!$B:$B, MATCH(O3, PriceBook!$A:$A, 0)) -> 20.7 | Q3: =L3 -> 1 | R3: =IF(Q3>=100, INDEX(PriceBook!$D:$D, MATCH("OPA140", PriceBook!$A:$A, 0)), IF(Q3>=10, INDEX(PriceBook!$C:$C, MATCH("OPA140", PriceBook!$A:$A, 0)), INDEX(PriceBook!$B:$B, MATCH("OPA140", PriceBook!$A:$A, 0)))) -> 3.69 | S3: =Q3*R3 -> 3.69 | T3: =L3 -> 1 | U3: =INDEX(PriceBook!$B:$B, MATCH("MCP6561", PriceBook!$A:$A, 0)) -> 0.473 | V3: =T3*U3 -> 0.473 | W3: =IF(L3>0,1,0) -> 1 | X3: =INDEX(PriceBook!$B:$B, MATCH("TLV3501", PriceBook!$A:$A, 0)) -> 3.51 | Y3: =W3*X3 -> 3.51 | Z3: =IF(I3>=100, INDEX(PriceBook!$D:$D, MATCH("TPL0102", PriceBook!$A:$A, 0)), IF(I3>=10, INDEX(PriceBook!$C:$C, MATCH("TPL0102", PriceBook!$A:$A, 0)), INDEX(PriceBook!$B:$B, MATCH("TPL0102", PriceBook!$A:$A, 0)))) -> 2.52 | AA3: =I3*Z3 -> 5.04 | AB3: =INDEX(PriceBook!$B:$B, MATCH("TMUX1108", PriceBook!$A:$A, 0)) -> 2.86 | AC3: =J3*AB3 -> 0 | AD3: 4 | AE3: =K3*AD3 -> 4 | AF3: =IF(L3>=5,1,0) -> 0 | AG3: =INDEX(PriceBook!$B:$B, MATCH("ADR4550", PriceBook!$A:$A, 0)) -> 7.49 | AH3: =AF3*AG3 -> 0 | AI3: =IF(L3>=5,1,0) -> 0 | AJ3: =INDEX(PriceBook!$B:$B, MATCH("LT3042", PriceBook!$A:$A, 0)) -> 7.82 | AK3: =AI3*AJ3 -> 0 | AL3: =N3 -> 19.82 | AM3: =P3 -> 20.7 | AN3: =S3+V3+Y3+AA3+AC3+AE3+AH3+AK3+AL3+AM3 -> 57.233 | AO3: =AN3*Assumptions!$B$2 -> 13.16359 | AP3: =I3*INDEX(PriceBook!$E:$E, MATCH("TPL0102", PriceBook!$A:$A, 0))+J3*INDEX(PriceBook!$E:$E, MATCH("TMUX1108", PriceBook!$A:$A, 0))+K3*INDEX(PriceBook!$E:$E, MATCH("ADG2128", PriceBook!$A:$A, 0))+L3*INDEX(PriceBook!$E:$E, MATCH("OPA140", PriceBook!$A:$A, 0))+L3*INDEX(PriceBook!$E:$E, MATCH("MCP6561", PriceBook!$A:$A, 0))+IF(L3>0, INDEX(PriceBook!$E:$E, MATCH("TLV3501", PriceBook!$A:$A, 0)), 0)+INDEX(PriceBook!$E:$E, MATCH(M3, PriceBook!$A:$A, 0))+IF(L3>=5, INDEX(PriceBook!$E:$E, MATCH("ADR4550", PriceBook!$A:$A, 0)), 0)+IF(L3>=5, INDEX(PriceBook!$E:$E, MATCH("LT3042", PriceBook!$A:$A, 0)), 0) -> 107 | AQ3: =Assumptions!$B$6+Assumptions!$B$10*SUM(Tiers!C3:L3) -> 30.05 | AR3: =AN3+AO3+AQ3 -> 100.44659 | AS3: =AR3*Assumptions!$B$2 -> 23.102716 | AT3: =AR3+AS3 -> 123.54931 | AU3: =IF(AT3<=2000, CEILING(AT3, 250), CEILING(AT3, 500)) -> 250
A4: 3x3→3 | B4: No | C4: 1 | D4: 3 | E4: 3 | F4: 3 | G4: 0 | H4: =IF(B4="Yes", C4*(D4+E4)*IF(G4>0, G4, F4) + IF(G4>0, G4*F4, 0), D4*E4*IF(G4>0, G4, F4) + IF(G4>0, G4*F4, 0)) -> 27 | I4: =H4 -> 27 | J4: 0 | K4: =CEILING(H4/Assumptions!$B$8,1) -> 4 | L4: =F4+G4 -> 3 | M4: =IF(LEFT(A4,4)="€100","ADS1115",IF(LEFT(A4,4)="€250","ADS1115","ADS1263")) -> ADS1263 | N4: =INDEX(PriceBook!$B:$B, MATCH(M4, PriceBook!$A:$A, 0)) -> 19.82 | O4: =IF(LEFT(A4,4)="€100","PICO2",IF(LEFT(A4,4)="€250","PICO2","NUCLEO_U575")) -> NUCLEO_U575 | P4: =INDEX(PriceBook!$B:$B, MATCH(O4, PriceBook!$A:$A, 0)) -> 20.7 | Q4: =L4 -> 3 | R4: =IF(Q4>=100, INDEX(PriceBook!$D:$D, MATCH("OPA140", PriceBook!$A:$A, 0)), IF(Q4>=10, INDEX(PriceBook!$C:$C, MATCH("OPA140", PriceBook!$A:$A, 0)), INDEX(PriceBook!$B:$B, MATCH("OPA140", PriceBook!$A:$A, 0)))) -> 3.69 | S4: =Q4*R4 -> 11.07 | T4: =L4 -> 3 | U4: =INDEX(PriceBook!$B:$B, MATCH("MCP6561", PriceBook!$A:$A, 0)) -> 0.473 | V4: =T4*U4 -> 1.419 | W4: =IF(L4>0,1,0) -> 1 | X4: =INDEX(PriceBook!$B:$B, MATCH("TLV3501", PriceBook!$A:$A, 0)) -> 3.51 | Y4: =W4*X4 -> 3.51 | Z4: =IF(I4>=100, INDEX(PriceBook!$D:$D, MATCH("TPL0102", PriceBook!$A:$A, 0)), IF(I4>=10, INDEX(PriceBook!$C:$C, MATCH("TPL0102", PriceBook!$A:$A, 0)), INDEX(PriceBook!$B:$B, MATCH("TPL0102", PriceBook!$A:$A, 0)))) -> 1.87 | AA4: =I4*Z4 -> 50.49 | AB4: =INDEX(PriceBook!$B:$B, MATCH("TMUX1108", PriceBook!$A:$A, 0)) -> 2.86 | AC4: =J4*AB4 -> 0 | AD4: 4 | AE4: =K4*AD4 -> 16 | AF4: =IF(L4>=5,1,0) -> 0 | AG4: =INDEX(PriceBook!$B:$B, MATCH("ADR4550", PriceBook!$A:$A, 0)) -> 7.49 | AH4: =AF4*AG4 -> 0 | AI4: =IF(L4>=5,1,0) -> 0 | AJ4: =INDEX(PriceBook!$B:$B, MATCH("LT3042", PriceBook!$A:$A, 0)) -> 7.82 | AK4: =AI4*AJ4 -> 0 | AL4: =N4 -> 19.82 | AM4: =P4 -> 20.7 | AN4: =S4+V4+Y4+AA4+AC4+AE4+AH4+AK4+AL4+AM4 -> 123.009 | AO4: =AN4*Assumptions!$B$2 -> 28.29207 | AP4: =I4*INDEX(PriceBook!$E:$E, MATCH("TPL0102", PriceBook!$A:$A, 0))+J4*INDEX(PriceBook!$E:$E, MATCH("TMUX1108", PriceBook!$A:$A, 0))+K4*INDEX(PriceBook!$E:$E, MATCH("ADG2128", PriceBook!$A:$A, 0))+L4*INDEX(PriceBook!$E:$E, MATCH("OPA140", PriceBook!$A:$A, 0))+L4*INDEX(PriceBook!$E:$E, MATCH("MCP6561", PriceBook!$A:$A, 0))+IF(L4>0, INDEX(PriceBook!$E:$E, MATCH("TLV3501", PriceBook!$A:$A, 0)), 0)+INDEX(PriceBook!$E:$E, MATCH(M4, PriceBook!$A:$A, 0))+IF(L4>=5, INDEX(PriceBook!$E:$E, MATCH("ADR4550", PriceBook!$A:$A, 0)), 0)+IF(L4>=5, INDEX(PriceBook!$E:$E, MATCH("LT3042", PriceBook!$A:$A, 0)), 0) -> 579 | AQ4: =Assumptions!$B$6+Assumptions!$B$10*SUM(Tiers!C4:L4) -> 30.355 | AR4: =AN4+AO4+AQ4 -> 181.65607 | AS4: =AR4*Assumptions!$B$2 -> 41.780896 | AT4: =AR4+AS4 -> 223.43697 | AU4: =IF(AT4<=2000, CEILING(AT4, 250), CEILING(AT4, 500)) -> 250
A5: 3x3→3 | B5: Yes | C5: 1 | D5: 3 | E5: 3 | F5: 3 | G5: 0 | H5: =IF(B5="Yes", C5*(D5+E5)*IF(G5>0, G5, F5) + IF(G5>0, G5*F5, 0), D5*E5*IF(G5>0, G5, F5) + IF(G5>0, G5*F5, 0)) -> 18 | I5: =H5 -> 18 | J5: 0 | K5: =CEILING(H5/Assumptions!$B$8,1) -> 3 | L5: =F5+G5 -> 3 | M5: =IF(LEFT(A5,4)="€100","ADS1115",IF(LEFT(A5,4)="€250","ADS1115","ADS1263")) -> ADS1263 | N5: =INDEX(PriceBook!$B:$B, MATCH(M5, PriceBook!$A:$A, 0)) -> 19.82 | O5: =IF(LEFT(A5,4)="€100","PICO2",IF(LEFT(A5,4)="€250","PICO2","NUCLEO_U575")) -> NUCLEO_U575 | P5: =INDEX(PriceBook!$B:$B, MATCH(O5, PriceBook!$A:$A, 0)) -> 20.7 | Q5: =L5 -> 3 | R5: =IF(Q5>=100, INDEX(PriceBook!$D:$D, MATCH("OPA140", PriceBook!$A:$A, 0)), IF(Q5>=10, INDEX(PriceBook!$C:$C, MATCH("OPA140", PriceBook!$A:$A, 0)), INDEX(PriceBook!$B:$B, MATCH("OPA140", PriceBook!$A:$A, 0)))) -> 3.69 | S5: =Q5*R5 -> 11.07 | T5: =L5 -> 3 | U5: =INDEX(PriceBook!$B:$B, MATCH("MCP6561", PriceBook!$A:$A, 0)) -> 0.473 | V5: =T5*U5 -> 1.419 | W5: =IF(L5>0,1,0) -> 1 | X5: =INDEX(PriceBook!$B:$B, MATCH("TLV3501", PriceBook!$A:$A, 0)) -> 3.51 | Y5: =W5*X5 -> 3.51 | Z5: =IF(I5>=100, INDEX(PriceBook!$D:$D, MATCH("TPL0102", PriceBook!$A:$A, 0)), IF(I5>=10, INDEX(PriceBook!$C:$C, MATCH("TPL0102", PriceBook!$A:$A, 0)), INDEX(PriceBook!$B:$B, MATCH("TPL0102", PriceBook!$A:$A, 0)))) -> 1.87 | AA5: =I5*Z5 -> 33.66 | AB5: =INDEX(PriceBook!$B:$B, MATCH("TMUX1108", PriceBook!$A:$A, 0)) -> 2.86 | AC5: =J5*AB5 -> 0 | AD5: 4 | AE5: =K5*AD5 -> 12 | AF5: =IF(L5>=5,1,0) -> 0 | AG5: =INDEX(PriceBook!$B:$B, MATCH("ADR4550", PriceBook!$A:$A, 0)) -> 7.49 | AH5: =AF5*AG5 -> 0 | AI5: =IF(L5>=5,1,0) -> 0 | AJ5: =INDEX(PriceBook!$B:$B, MATCH("LT3042", PriceBook!$A:$A, 0)) -> 7.82 | AK5: =AI5*AJ5 -> 0 | AL5: =N5 -> 19.82 | AM5: =P5 -> 20.7 | AN5: =S5+V5+Y5+AA5+AC5+AE5+AH5+AK5+AL5+AM5 -> 102.179 | AO5: =AN5*Assumptions!$B$2 -> 23.50117 | AP5: =I5*INDEX(PriceBook!$E:$E, MATCH("TPL0102", PriceBook!$A:$A, 0))+J5*INDEX(PriceBook!$E:$E, MATCH("TMUX1108", PriceBook!$A:$A, 0))+K5*INDEX(PriceBook!$E:$E, MATCH("ADG2128", PriceBook!$A:$A, 0))+L5*INDEX(PriceBook!$E:$E, MATCH("OPA140", PriceBook!$A:$A, 0))+L5*INDEX(PriceBook!$E:$E, MATCH("MCP6561", PriceBook!$A:$A, 0))+IF(L5>0, INDEX(PriceBook!$E:$E, MATCH("TLV3501", PriceBook!$A:$A, 0)), 0)+INDEX(PriceBook!$E:$E, MATCH(M5, PriceBook!$A:$A, 0))+IF(L5>=5, INDEX(PriceBook!$E:$E, MATCH("ADR4550", PriceBook!$A:$A, 0)), 0)+IF(L5>=5, INDEX(PriceBook!$E:$E, MATCH("LT3042", PriceBook!$A:$A, 0)), 0) -> 421 | AQ5: =Assumptions!$B$6+Assumptions!$B$10*SUM(Tiers!C5:L5) -> 30.26 | AR5: =AN5+AO5+AQ5 -> 155.94017 | AS5: =AR5*Assumptions!$B$2 -> 35.866239 | AT5: =AR5+AS5 -> 191.80641 | AU5: =IF(AT5<=2000, CEILING(AT5, 250), CEILING(AT5, 500)) -> 250
A6: 5x5→5 | B6: No | C6: 1 | D6: 5 | E6: 5 | F6: 5 | G6: 0 | H6: =IF(B6="Yes", C6*(D6+E6)*IF(G6>0, G6, F6) + IF(G6>0, G6*F6, 0), D6*E6*IF(G6>0, G6, F6) + IF(G6>0, G6*F6, 0)) -> 125 | I6: =H6 -> 125 | J6: 0 | K6: =CEILING(H6/Assumptions!$B$8,1) -> 16 | L6: =F6+G6 -> 5 | M6: =IF(LEFT(A6,4)="€100","ADS1115",IF(LEFT(A6,4)="€250","ADS1115","ADS1263")) -> ADS1263 | N6: =INDEX(PriceBook!$B:$B, MATCH(M6, PriceBook!$A:$A, 0)) -> 19.82 | O6: =IF(LEFT(A6,4)="€100","PICO2",IF(LEFT(A6,4)="€250","PICO2","NUCLEO_U575")) -> NUCLEO_U575 | P6: =INDEX(PriceBook!$B:$B, MATCH(O6, PriceBook!$A:$A, 0)) -> 20.7 | Q6: =L6 -> 5 | R6: =IF(Q6>=100, INDEX(PriceBook!$D:$D, MATCH("OPA140", PriceBook!$A:$A, 0)), IF(Q6>=10, INDEX(PriceBook!$C:$C, MATCH("OPA140", PriceBook!$A:$A, 0)), INDEX(PriceBook!$B:$B, MATCH("OPA140", PriceBook!$A:$A, 0)))) -> 3.69 | S6: =Q6*R6 -> 18.45 | T6: =L6 -> 5 | U6: =INDEX(PriceBook!$B:$B, MATCH("MCP6561", PriceBook!$A:$A, 0)) -> 0.473 | V6: =T6*U6 -> 2.365 | W6: =IF(L6>0,1,0) -> 1 | X6: =INDEX(PriceBook!$B:$B, MATCH("TLV3501", PriceBook!$A:$A, 0)) -> 3.51 | Y6: =W6*X6 -> 3.51 | Z6: =IF(I6>=100, INDEX(PriceBook!$D:$D, MATCH("TPL0102", PriceBook!$A:$A, 0)), IF(I6>=10, INDEX(PriceBook!$C:$C, MATCH("TPL0102", PriceBook!$A:$A, 0)), INDEX(PriceBook!$B:$B, MATCH("TPL0102", PriceBook!$A:$A, 0)))) -> 1.54 | AA6: =I6*Z6 -> 192.5 | AB6: =INDEX(PriceBook!$B:$B, MATCH("TMUX1108", PriceBook!$A:$A, 0)) -> 2.86 | AC6: =J6*AB6 -> 0 | AD6: 4 | AE6: =K6*AD6 -> 64 | AF6: =IF(L6>=5,1,0) -> 1 | AG6: =INDEX(PriceBook!$B:$B, MATCH("ADR4550", PriceBook!$A:$A, 0)) -> 7.49 | AH6: =AF6*AG6 -> 7.49 | AI6: =IF(L6>=5,1,0) -> 1 | AJ6: =INDEX(PriceBook!$B:$B, MATCH("LT3042", PriceBook!$A:$A, 0)) -> 7.82 | AK6: =AI6*AJ6 -> 7.82 | AL6: =N6 -> 19.82 | AM6: =P6 -> 20.7 | AN6: =S6+V6+Y6+AA6+AC6+AE6+AH6+AK6+AL6+AM6 -> 336.655 | AO6: =AN6*Assumptions!$B$2 -> 77.43065 | AP6: =I6*INDEX(PriceBook!$E:$E, MATCH("TPL0102", PriceBook!$A:$A, 0))+J6*INDEX(PriceBook!$E:$E, MATCH("TMUX1108", PriceBook!$A:$A, 0))+K6*INDEX(PriceBook!$E:$E, MATCH("ADG2128", PriceBook!$A:$A, 0))+L6*INDEX(PriceBook!$E:$E, MATCH("OPA140", PriceBook!$A:$A, 0))+L6*INDEX(PriceBook!$E:$E, MATCH("MCP6561", PriceBook!$A:$A, 0))+IF(L6>0, INDEX(PriceBook!$E:$E, MATCH("TLV3501", PriceBook!$A:$A, 0)), 0)+INDEX(PriceBook!$E:$E, MATCH(M6, PriceBook!$A:$A, 0))+IF(L6>=5, INDEX(PriceBook!$E:$E, MATCH("ADR4550", PriceBook!$A:$A, 0)), 0)+IF(L6>=5, INDEX(PriceBook!$E:$E, MATCH("LT3042", PriceBook!$A:$A, 0)), 0) -> 2379 | AQ6: =Assumptions!$B$6+Assumptions!$B$10*SUM(Tiers!C6:L6) -> 31.435 | AR6: =AN6+AO6+AQ6 -> 445.52065 | AS6: =AR6*Assumptions!$B$2 -> 102.46975 | AT6: =AR6+AS6 -> 547.9904 | AU6: =IF(AT6<=2000, CEILING(AT6, 250), CEILING(AT6, 500)) -> 750
A7: 5x5→5 | B7: Yes | C7: 1 | D7: 5 | E7: 5 | F7: 5 | G7: 0 | H7: =IF(B7="Yes", C7*(D7+E7)*IF(G7>0, G7, F7) + IF(G7>0, G7*F7, 0), D7*E7*IF(G7>0, G7, F7) + IF(G7>0, G7*F7, 0)) -> 50 | I7: =H7 -> 50 | J7: 0 | K7: =CEILING(H7/Assumptions!$B$8,1) -> 7 | L7: =F7+G7 -> 5 | M7: =IF(LEFT(A7,4)="€100","ADS1115",IF(LEFT(A7,4)="€250","ADS1115","ADS1263")) -> ADS1263 | N7: =INDEX(PriceBook!$B:$B, MATCH(M7, PriceBook!$A:$A, 0)) -> 19.82 | O7: =IF(LEFT(A7,4)="€100","PICO2",IF(LEFT(A7,4)="€250","PICO2","NUCLEO_U575")) -> NUCLEO_U575 | P7: =INDEX(PriceBook!$B:$B, MATCH(O7, PriceBook!$A:$A, 0)) -> 20.7 | Q7: =L7 -> 5 | R7: =IF(Q7>=100, INDEX(PriceBook!$D:$D, MATCH("OPA140", PriceBook!$A:$A, 0)), IF(Q7>=10, INDEX(PriceBook!$C:$C, MATCH("OPA140", PriceBook!$A:$A, 0)), INDEX(PriceBook!$B:$B, MATCH("OPA140", PriceBook!$A:$A, 0)))) -> 3.69 | S7: =Q7*R7 -> 18.45 | T7: =L7 -> 5 | U7: =INDEX(PriceBook!$B:$B, MATCH("MCP6561", PriceBook!$A:$A, 0)) -> 0.473 | V7: =T7*U7 -> 2.365 | W7: =IF(L7>0,1,0) -> 1 | X7: =INDEX(PriceBook!$B:$B, MATCH("TLV3501", PriceBook!$A:$A, 0)) -> 3.51 | Y7: =W7*X7 -> 3.51 | Z7: =IF(I7>=100, INDEX(PriceBook!$D:$D, MATCH("TPL0102", PriceBook!$A:$A, 0)), IF(I7>=10, INDEX(PriceBook!$C:$C, MATCH("TPL0102", PriceBook!$A:$A, 0)), INDEX(PriceBook!$B:$B, MATCH("TPL0102", PriceBook!$A:$A, 0)))) -> 1.87 | AA7: =I7*Z7 -> 93.5 | AB7: =INDEX(PriceBook!$B:$B, MATCH("TMUX1108", PriceBook!$A:$A, 0)) -> 2.86 | AC7: =J7*AB7 -> 0 | AD7: 4 | AE7: =K7*AD7 -> 28 | AF7: =IF(L7>=5,1,0) -> 1 | AG7: =INDEX(PriceBook!$B:$B, MATCH("ADR4550", PriceBook!$A:$A, 0)) -> 7.49 | AH7: =AF7*AG7 -> 7.49 | AI7: =IF(L7>=5,1,0) -> 1 | AJ7: =INDEX(PriceBook!$B:$B, MATCH("LT3042", PriceBook!$A:$A, 0)) -> 7.82 | AK7: =AI7*AJ7 -> 7.82 | AL7: =N7 -> 19.82 | AM7: =P7 -> 20.7 | AN7: =S7+V7+Y7+AA7+AC7+AE7+AH7+AK7+AL7+AM7 -> 201.655 | AO7: =AN7*Assumptions!$B$2 -> 46.38065 | AP7: =I7*INDEX(PriceBook!$E:$E, MATCH("TPL0102", PriceBook!$A:$A, 0))+J7*INDEX(PriceBook!$E:$E, MATCH("TMUX1108", PriceBook!$A:$A, 0))+K7*INDEX(PriceBook!$E:$E, MATCH("ADG2128", PriceBook!$A:$A, 0))+L7*INDEX(PriceBook!$E:$E, MATCH("OPA140", PriceBook!$A:$A, 0))+L7*INDEX(PriceBook!$E:$E, MATCH("MCP6561", PriceBook!$A:$A, 0))+IF(L7>0, INDEX(PriceBook!$E:$E, MATCH("TLV3501", PriceBook!$A:$A, 0)), 0)+INDEX(PriceBook!$E:$E, MATCH(M7, PriceBook!$A:$A, 0))+IF(L7>=5, INDEX(PriceBook!$E:$E, MATCH("ADR4550", PriceBook!$A:$A, 0)), 0)+IF(L7>=5, INDEX(PriceBook!$E:$E, MATCH("LT3042", PriceBook!$A:$A, 0)), 0) -> 1041 | AQ7: =Assumptions!$B$6+Assumptions!$B$10*SUM(Tiers!C7:L7) -> 30.64 | AR7: =AN7+AO7+AQ7 -> 278.67565 | AS7: =AR7*Assumptions!$B$2 -> 64.095399 | AT7: =AR7+AS7 -> 342.77105 | AU7: =IF(AT7<=2000, CEILING(AT7, 250), CEILING(AT7, 500)) -> 500
A8: 7x7→5 | B8: No | C8: 1 | D8: 7 | E8: 7 | F8: 5 | G8: 0 | H8: =IF(B8="Yes", C8*(D8+E8)*IF(G8>0, G8, F8) + IF(G8>0, G8*F8, 0), D8*E8*IF(G8>0, G8, F8) + IF(G8>0, G8*F8, 0)) -> 245 | I8: =H8 -> 245 | J8: 0 | K8: =CEILING(H8/Assumptions!$B$8,1) -> 31 | L8: =F8+G8 -> 5 | M8: =IF(LEFT(A8,4)="€100","ADS1115",IF(LEFT(A8,4)="€250","ADS1115","ADS1263")) -> ADS1263 | N8: =INDEX(PriceBook!$B:$B, MATCH(M8, PriceBook!$A:$A, 0)) -> 19.82 | O8: =IF(LEFT(A8,4)="€100","PICO2",IF(LEFT(A8,4)="€250","PICO2","NUCLEO_U575")) -> NUCLEO_U575 | P8: =INDEX(PriceBook!$B:$B, MATCH(O8, PriceBook!$A:$A, 0)) -> 20.7 | Q8: =L8 -> 5 | R8: =IF(Q8>=100, INDEX(PriceBook!$D:$D, MATCH("OPA140", PriceBook!$A:$A, 0)), IF(Q8>=10, INDEX(PriceBook!$C:$C, MATCH("OPA140", PriceBook!$A:$A, 0)), INDEX(PriceBook!$B:$B, MATCH("OPA140", PriceBook!$A:$A, 0)))) -> 3.69 | S8: =Q8*R8 -> 18.45 | T8: =L8 -> 5 | U8: =INDEX(PriceBook!$B:$B, MATCH("MCP6561", PriceBook!$A:$A, 0)) -> 0.473 | V8: =T8*U8 -> 2.365 | W8: =IF(L8>0,1,0) -> 1 | X8: =INDEX(PriceBook!$B:$B, MATCH("TLV3501", PriceBook!$A:$A, 0)) -> 3.51 | Y8: =W8*X8 -> 3.51 | Z8: =IF(I8>=100, INDEX(PriceBook!$D:$D, MATCH("TPL0102", PriceBook!$A:$A, 0)), IF(I8>=10, INDEX(PriceBook!$C:$C, MATCH("TPL0102", PriceBook!$A:$A, 0)), INDEX(PriceBook!$B:$B, MATCH("TPL0102", PriceBook!$A:$A, 0)))) -> 1.54 | AA8: =I8*Z8 -> 377.3 | AB8: =INDEX(PriceBook!$B:$B, MATCH("TMUX1108", PriceBook!$A:$A, 0)) -> 2.86 | AC8: =J8*AB8 -> 0 | AD8: 4 | AE8: =K8*AD8 -> 124 | AF8: =IF(L8>=5,1,0) -> 1 | AG8: =INDEX(PriceBook!$B:$B, MATCH("ADR4550", PriceBook!$A:$A, 0)) -> 7.49 | AH8: =AF8*AG8 -> 7.49 | AI8: =IF(L8>=5,1,0) -> 1 | AJ8: =INDEX(PriceBook!$B:$B, MATCH("LT3042", PriceBook!$A:$A, 0)) -> 7.82 | AK8: =AI8*AJ8 -> 7.82 | AL8: =N8 -> 19.82 | AM8: =P8 -> 20.7 | AN8: =S8+V8+Y8+AA8+AC8+AE8+AH8+AK8+AL8+AM8 -> 581.455 | AO8: =AN8*Assumptions!$B$2 -> 133.73465 | AP8: =I8*INDEX(PriceBook!$E:$E, MATCH("TPL0102", PriceBook!$A:$A, 0))+J8*INDEX(PriceBook!$E:$E, MATCH("TMUX1108", PriceBook!$A:$A, 0))+K8*INDEX(PriceBook!$E:$E, MATCH("ADG2128", PriceBook!$A:$A, 0))+L8*INDEX(PriceBook!$E:$E, MATCH("OPA140", PriceBook!$A:$A, 0))+L8*INDEX(PriceBook!$E:$E, MATCH("MCP6561", PriceBook!$A:$A, 0))+IF(L8>0, INDEX(PriceBook!$E:$E, MATCH("TLV3501", PriceBook!$A:$A, 0)), 0)+INDEX(PriceBook!$E:$E, MATCH(M8, PriceBook!$A:$A, 0))+IF(L8>=5, INDEX(PriceBook!$E:$E, MATCH("ADR4550", PriceBook!$A:$A, 0)), 0)+IF(L8>=5, INDEX(PriceBook!$E:$E, MATCH("LT3042", PriceBook!$A:$A, 0)), 0) -> 4539 | AQ8: =Assumptions!$B$6+Assumptions!$B$10*SUM(Tiers!C8:L8) -> 32.73 | AR8: =AN8+AO8+AQ8 -> 747.91965 | AS8: =AR8*Assumptions!$B$2 -> 172.02152 | AT8: =AR8+AS8 -> 919.94117 | AU8: =IF(AT8<=2000, CEILING(AT8, 250), CEILING(AT8, 500)) -> 1000
A9: 7x7→5 | B9: Yes | C9: 1 | D9: 7 | E9: 7 | F9: 5 | G9: 0 | H9: =IF(B9="Yes", C9*(D9+E9)*IF(G9>0, G9, F9) + IF(G9>0, G9*F9, 0), D9*E9*IF(G9>0, G9, F9) + IF(G9>0, G9*F9, 0)) -> 70 | I9: =H9 -> 70 | J9: 0 | K9: =CEILING(H9/Assumptions!$B$8,1) -> 9 | L9: =F9+G9 -> 5 | M9: =IF(LEFT(A9,4)="€100","ADS1115",IF(LEFT(A9,4)="€250","ADS1115","ADS1263")) -> ADS1263 | N9: =INDEX(PriceBook!$B:$B, MATCH(M9, PriceBook!$A:$A, 0)) -> 19.82 | O9: =IF(LEFT(A9,4)="€100","PICO2",IF(LEFT(A9,4)="€250","PICO2","NUCLEO_U575")) -> NUCLEO_U575 | P9: =INDEX(PriceBook!$B:$B, MATCH(O9, PriceBook!$A:$A, 0)) -> 20.7 | Q9: =L9 -> 5 | R9: =IF(Q9>=100, INDEX(PriceBook!$D:$D, MATCH("OPA140", PriceBook!$A:$A, 0)), IF(Q9>=10, INDEX(PriceBook!$C:$C, MATCH("OPA140", PriceBook!$A:$A, 0)), INDEX(PriceBook!$B:$B, MATCH("OPA140", PriceBook!$A:$A, 0)))) -> 3.69 | S9: =Q9*R9 -> 18.45 | T9: =L9 -> 5 | U9: =INDEX(PriceBook!$B:$B, MATCH("MCP6561", PriceBook!$A:$A, 0)) -> 0.473 | V9: =T9*U9 -> 2.365 | W9: =IF(L9>0,1,0) -> 1 | X9: =INDEX(PriceBook!$B:$B, MATCH("TLV3501", PriceBook!$A:$A, 0)) -> 3.51 | Y9: =W9*X9 -> 3.51 | Z9: =IF(I9>=100, INDEX(PriceBook!$D:$D, MATCH("TPL0102", PriceBook!$A:$A, 0)), IF(I9>=10, INDEX(PriceBook!$C:$C, MATCH("TPL0102", PriceBook!$A:$A, 0)), INDEX(PriceBook!$B:$B, MATCH("TPL0102", PriceBook!$A:$A, 0)))) -> 1.87 | AA9: =I9*Z9 -> 130.9 | AB9: =INDEX(PriceBook!$B:$B, MATCH("TMUX1108", PriceBook!$A:$A, 0)) -> 2.86 | AC9: =J9*AB9 -> 0 | AD9: 4 | AE9: =K9*AD9 -> 36 | AF9: =IF(L9>=5,1,0) -> 1 | AG9: =INDEX(PriceBook!$B:$B, MATCH("ADR4550", PriceBook!$A:$A, 0)) -> 7.49 | AH9: =AF9*AG9 -> 7.49 | AI9: =IF(L9>=5,1,0) -> 1 | AJ9: =INDEX(PriceBook!$B:$B, MATCH("LT3042", PriceBook!$A:$A, 0)) -> 7.82 | AK9: =AI9*AJ9 -> 7.82 | AL9: =N9 -> 19.82 | AM9: =P9 -> 20.7 | AN9: =S9+V9+Y9+AA9+AC9+AE9+AH9+AK9+AL9+AM9 -> 247.055 | AO9: =AN9*Assumptions!$B$2 -> 56.82265 | AP9: =I9*INDEX(PriceBook!$E:$E, MATCH("TPL0102", PriceBook!$A:$A, 0))+J9*INDEX(PriceBook!$E:$E, MATCH("TMUX1108", PriceBook!$A:$A, 0))+K9*INDEX(PriceBook!$E:$E, MATCH("ADG2128", PriceBook!$A:$A, 0))+L9*INDEX(PriceBook!$E:$E, MATCH("OPA140", PriceBook!$A:$A, 0))+L9*INDEX(PriceBook!$E:$E, MATCH("MCP6561", PriceBook!$A:$A, 0))+IF(L9>0, INDEX(PriceBook!$E:$E, MATCH("TLV3501", PriceBook!$A:$A, 0)), 0)+INDEX(PriceBook!$E:$E, MATCH(M9, PriceBook!$A:$A, 0))+IF(L9>=5, INDEX(PriceBook!$E:$E, MATCH("ADR4550", PriceBook!$A:$A, 0)), 0)+IF(L9>=5, INDEX(PriceBook!$E:$E, MATCH("LT3042", PriceBook!$A:$A, 0)), 0) -> 1385 | AQ9: =Assumptions!$B$6+Assumptions!$B$10*SUM(Tiers!C9:L9) -> 30.87 | AR9: =AN9+AO9+AQ9 -> 334.74765 | AS9: =AR9*Assumptions!$B$2 -> 76.991959 | AT9: =AR9+AS9 -> 411.73961 | AU9: =IF(AT9<=2000, CEILING(AT9, 250), CEILING(AT9, 500)) -> 500
A10: 7x7→10 | B10: No | C10: 1 | D10: 7 | E10: 7 | F10: 10 | G10: 0 | H10: =IF(B10="Yes", C10*(D10+E10)*IF(G10>0, G10, F10) + IF(G10>0, G10*F10, 0), D10*E10*IF(G10>0, G10, F10) + IF(G10>0, G10*F10, 0)) -> 490 | I10: =H10 -> 490 | J10: 0 | K10: =CEILING(H10/Assumptions!$B$8,1) -> 62 | L10: =F10+G10 -> 10 | M10: =IF(LEFT(A10,4)="€100","ADS1115",IF(LEFT(A10,4)="€250","ADS1115","ADS1263")) -> ADS1263 | N10: =INDEX(PriceBook!$B:$B, MATCH(M10, PriceBook!$A:$A, 0)) -> 19.82 | O10: =IF(LEFT(A10,4)="€100","PICO2",IF(LEFT(A10,4)="€250","PICO2","NUCLEO_U575")) -> NUCLEO_U575 | P10: =INDEX(PriceBook!$B:$B, MATCH(O10, PriceBook!$A:$A, 0)) -> 20.7 | Q10: =L10 -> 10 | R10: =IF(Q10>=100, INDEX(PriceBook!$D:$D, MATCH("OPA140", PriceBook!$A:$A, 0)), IF(Q10>=10, INDEX(PriceBook!$C:$C, MATCH("OPA140", PriceBook!$A:$A, 0)), INDEX(PriceBook!$B:$B, MATCH("OPA140", PriceBook!$A:$A, 0)))) -> 2.8 | S10: =Q10*R10 -> 28 | T10: =L10 -> 10 | U10: =INDEX(PriceBook!$B:$B, MATCH("MCP6561", PriceBook!$A:$A, 0)) -> 0.473 | V10: =T10*U10 -> 4.73 | W10: =IF(L10>0,1,0) -> 1 | X10: =INDEX(PriceBook!$B:$B, MATCH("TLV3501", PriceBook!$A:$A, 0)) -> 3.51 | Y10: =W10*X10 -> 3.51 | Z10: =IF(I10>=100, INDEX(PriceBook!$D:$D, MATCH("TPL0102", PriceBook!$A:$A, 0)), IF(I10>=10, INDEX(PriceBook!$C:$C, MATCH("TPL0102", PriceBook!$A:$A, 0)), INDEX(PriceBook!$B:$B, MATCH("TPL0102", PriceBook!$A:$A, 0)))) -> 1.54 | AA10: =I10*Z10 -> 754.6 | AB10: =INDEX(PriceBook!$B:$B, MATCH("TMUX1108", PriceBook!$A:$A, 0)) -> 2.86 | AC10: =J10*AB10 -> 0 | AD10: 4 | AE10: =K10*AD10 -> 248 | AF10: =IF(L10>=5,1,0) -> 1 | AG10: =INDEX(PriceBook!$B:$B, MATCH("ADR4550", PriceBook!$A:$A, 0)) -> 7.49 | AH10: =AF10*AG10 -> 7.49 | AI10: =IF(L10>=5,1,0) -> 1 | AJ10: =INDEX(PriceBook!$B:$B, MATCH("LT3042", PriceBook!$A:$A, 0)) -> 7.82 | AK10: =AI10*AJ10 -> 7.82 | AL10: =N10 -> 19.82 | AM10: =P10 -> 20.7 | AN10: =S10+V10+Y10+AA10+AC10+AE10+AH10+AK10+AL10+AM10 -> 1094.67 | AO10: =AN10*Assumptions!$B$2 -> 251.7741 | AP10: =I10*INDEX(PriceBook!$E:$E, MATCH("TPL0102", PriceBook!$A:$A, 0))+J10*INDEX(PriceBook!$E:$E, MATCH("TMUX1108", PriceBook!$A:$A, 0))+K10*INDEX(PriceBook!$E:$E, MATCH("ADG2128", PriceBook!$A:$A, 0))+L10*INDEX(PriceBook!$E:$E, MATCH("OPA140", PriceBook!$A:$A, 0))+L10*INDEX(PriceBook!$E:$E, MATCH("MCP6561", PriceBook!$A:$A, 0))+IF(L10>0, INDEX(PriceBook!$E:$E, MATCH("TLV3501", PriceBook!$A:$A, 0)), 0)+INDEX(PriceBook!$E:$E, MATCH(M10, PriceBook!$A:$A, 0))+IF(L10>=5, INDEX(PriceBook!$E:$E, MATCH("ADR4550", PriceBook!$A:$A, 0)), 0)+IF(L10>=5, INDEX(PriceBook!$E:$E, MATCH("LT3042", PriceBook!$A:$A, 0)), 0) -> 9026 | AQ10: =Assumptions!$B$6+Assumptions!$B$10*SUM(Tiers!C10:L10) -> 35.385 | AR10: =AN10+AO10+AQ10 -> 1381.8291 | AS10: =AR10*Assumptions!$B$2 -> 317.82069 | AT10: =AR10+AS10 -> 1699.6498 | AU10: =IF(AT10<=2000, CEILING(AT10, 250), CEILING(AT10, 500)) -> 1750
A11: 7x7→10 | B11: Yes | C11: 1 | D11: 7 | E11: 7 | F11: 10 | G11: 0 | H11: =IF(B11="Yes", C11*(D11+E11)*IF(G11>0, G11, F11) + IF(G11>0, G11*F11, 0), D11*E11*IF(G11>0, G11, F11) + IF(G11>0, G11*F11, 0)) -> 140 | I11: =H11 -> 140 | J11: 0 | K11: =CEILING(H11/Assumptions!$B$8,1) -> 18 | L11: =F11+G11 -> 10 | M11: =IF(LEFT(A11,4)="€100","ADS1115",IF(LEFT(A11,4)="€250","ADS1115","ADS1263")) -> ADS1263 | N11: =INDEX(PriceBook!$B:$B, MATCH(M11, PriceBook!$A:$A, 0)) -> 19.82 | O11: =IF(LEFT(A11,4)="€100","PICO2",IF(LEFT(A11,4)="€250","PICO2","NUCLEO_U575")) -> NUCLEO_U575 | P11: =INDEX(PriceBook!$B:$B, MATCH(O11, PriceBook!$A:$A, 0)) -> 20.7 | Q11: =L11 -> 10 | R11: =IF(Q11>=100, INDEX(PriceBook!$D:$D, MATCH("OPA140", PriceBook!$A:$A, 0)), IF(Q11>=10, INDEX(PriceBook!$C:$C, MATCH("OPA140", PriceBook!$A:$A, 0)), INDEX(PriceBook!$B:$B, MATCH("OPA140", PriceBook!$A:$A, 0)))) -> 2.8 | S11: =Q11*R11 -> 28 | T11: =L11 -> 10 | U11: =INDEX(PriceBook!$B:$B, MATCH("MCP6561", PriceBook!$A:$A, 0)) -> 0.473 | V11: =T11*U11 -> 4.73 | W11: =IF(L11>0,1,0) -> 1 | X11: =INDEX(PriceBook!$B:$B, MATCH("TLV3501", PriceBook!$A:$A, 0)) -> 3.51 | Y11: =W11*X11 -> 3.51 | Z11: =IF(I11>=100, INDEX(PriceBook!$D:$D, MATCH("TPL0102", PriceBook!$A:$A, 0)), IF(I11>=10, INDEX(PriceBook!$C:$C, MATCH("TPL0102", PriceBook!$A:$A, 0)), INDEX(PriceBook!$B:$B, MATCH("TPL0102", PriceBook!$A:$A, 0)))) -> 1.54 | AA11: =I11*Z11 -> 215.6 | AB11: =INDEX(PriceBook!$B:$B, MATCH("TMUX1108", PriceBook!$A:$A, 0)) -> 2.86 | AC11: =J11*AB11 -> 0 | AD11: 4 | AE11: =K11*AD11 -> 72 | AF11: =IF(L11>=5,1,0) -> 1 | AG11: =INDEX(PriceBook!$B:$B, MATCH("ADR4550", PriceBook!$A:$A, 0)) -> 7.49 | AH11: =AF11*AG11 -> 7.49 | AI11: =IF(L11>=5,1,0) -> 1 | AJ11: =INDEX(PriceBook!$B:$B, MATCH("LT3042", PriceBook!$A:$A, 0)) -> 7.82 | AK11: =AI11*AJ11 -> 7.82 | AL11: =N11 -> 19.82 | AM11: =P11 -> 20.7 | AN11: =S11+V11+Y11+AA11+AC11+AE11+AH11+AK11+AL11+AM11 -> 379.67 | AO11: =AN11*Assumptions!$B$2 -> 87.3241 | AP11: =I11*INDEX(PriceBook!$E:$E, MATCH("TPL0102", PriceBook!$A:$A, 0))+J11*INDEX(PriceBook!$E:$E, MATCH("TMUX1108", PriceBook!$A:$A, 0))+K11*INDEX(PriceBook!$E:$E, MATCH("ADG2128", PriceBook!$A:$A, 0))+L11*INDEX(PriceBook!$E:$E, MATCH("OPA140", PriceBook!$A:$A, 0))+L11*INDEX(PriceBook!$E:$E, MATCH("MCP6561", PriceBook!$A:$A, 0))+IF(L11>0, INDEX(PriceBook!$E:$E, MATCH("TLV3501", PriceBook!$A:$A, 0)), 0)+INDEX(PriceBook!$E:$E, MATCH(M11, PriceBook!$A:$A, 0))+IF(L11>=5, INDEX(PriceBook!$E:$E, MATCH("ADR4550", PriceBook!$A:$A, 0)), 0)+IF(L11>=5, INDEX(PriceBook!$E:$E, MATCH("LT3042", PriceBook!$A:$A, 0)), 0) -> 2718 | AQ11: =Assumptions!$B$6+Assumptions!$B$10*SUM(Tiers!C11:L11) -> 31.665 | AR11: =AN11+AO11+AQ11 -> 498.6591 | AS11: =AR11*Assumptions!$B$2 -> 114.69159 | AT11: =AR11+AS11 -> 613.35069 | AU11: =IF(AT11<=2000, CEILING(AT11, 250), CEILING(AT11, 500)) -> 750
A12: 7x7→16→10 | B12: No | C12: 1 | D12: 7 | E12: 7 | F12: 10 | G12: 16 | H12: =IF(B12="Yes", C12*(D12+E12)*IF(G12>0, G12, F12) + IF(G12>0, G12*F12, 0), D12*E12*IF(G12>0, G12, F12) + IF(G12>0, G12*F12, 0)) -> 944 | I12: =H12 -> 944 | J12: 0 | K12: =CEILING(H12/Assumptions!$B$8,1) -> 118 | L12: =F12+G12 -> 26 | M12: =IF(LEFT(A12,4)="€100","ADS1115",IF(LEFT(A12,4)="€250","ADS1115","ADS1263")) -> ADS1263 | N12: =INDEX(PriceBook!$B:$B, MATCH(M12, PriceBook!$A:$A, 0)) -> 19.82 | O12: =IF(LEFT(A12,4)="€100","PICO2",IF(LEFT(A12,4)="€250","PICO2","NUCLEO_U575")) -> NUCLEO_U575 | P12: =INDEX(PriceBook!$B:$B, MATCH(O12, PriceBook!$A:$A, 0)) -> 20.7 | Q12: =L12 -> 26 | R12: =IF(Q12>=100, INDEX(PriceBook!$D:$D, MATCH("OPA140", PriceBook!$A:$A, 0)), IF(Q12>=10, INDEX(PriceBook!$C:$C, MATCH("OPA140", PriceBook!$A:$A, 0)), INDEX(PriceBook!$B:$B, MATCH("OPA140", PriceBook!$A:$A, 0)))) -> 2.8 | S12: =Q12*R12 -> 72.8 | T12: =L12 -> 26 | U12: =INDEX(PriceBook!$B:$B, MATCH("MCP6561", PriceBook!$A:$A, 0)) -> 0.473 | V12: =T12*U12 -> 12.298 | W12: =IF(L12>0,1,0) -> 1 | X12: =INDEX(PriceBook!$B:$B, MATCH("TLV3501", PriceBook!$A:$A, 0)) -> 3.51 | Y12: =W12*X12 -> 3.51 | Z12: =IF(I12>=100, INDEX(PriceBook!$D:$D, MATCH("TPL0102", PriceBook!$A:$A, 0)), IF(I12>=10, INDEX(PriceBook!$C:$C, MATCH("TPL0102", PriceBook!$A:$A, 0)), INDEX(PriceBook!$B:$B, MATCH("TPL0102", PriceBook!$A:$A, 0)))) -> 1.54 | AA12: =I12*Z12 -> 1453.76 | AB12: =INDEX(PriceBook!$B:$B, MATCH("TMUX1108", PriceBook!$A:$A, 0)) -> 2.86 | AC12: =J12*AB12 -> 0 | AD12: 4 | AE12: =K12*AD12 -> 472 | AF12: =IF(L12>=5,1,0) -> 1 | AG12: =INDEX(PriceBook!$B:$B, MATCH("ADR4550", PriceBook!$A:$A, 0)) -> 7.49 | AH12: =AF12*AG12 -> 7.49 | AI12: =IF(L12>=5,1,0) -> 1 | AJ12: =INDEX(PriceBook!$B:$B, MATCH("LT3042", PriceBook!$A:$A, 0)) -> 7.82 | AK12: =AI12*AJ12 -> 7.82 | AL12: =N12 -> 19.82 | AM12: =P12 -> 20.7 | AN12: =S12+V12+Y12+AA12+AC12+AE12+AH12+AK12+AL12+AM12 -> 2070.198 | AO12: =AN12*Assumptions!$B$2 -> 476.14554 | AP12: =I12*INDEX(PriceBook!$E:$E, MATCH("TPL0102", PriceBook!$A:$A, 0))+J12*INDEX(PriceBook!$E:$E, MATCH("TMUX1108", PriceBook!$A:$A, 0))+K12*INDEX(PriceBook!$E:$E, MATCH("ADG2128", PriceBook!$A:$A, 0))+L12*INDEX(PriceBook!$E:$E, MATCH("OPA140", PriceBook!$A:$A, 0))+L12*INDEX(PriceBook!$E:$E, MATCH("MCP6561", PriceBook!$A:$A, 0))+IF(L12>0, INDEX(PriceBook!$E:$E, MATCH("TLV3501", PriceBook!$A:$A, 0)), 0)+INDEX(PriceBook!$E:$E, MATCH(M12, PriceBook!$A:$A, 0))+IF(L12>=5, INDEX(PriceBook!$E:$E, MATCH("ADR4550", PriceBook!$A:$A, 0)), 0)+IF(L12>=5, INDEX(PriceBook!$E:$E, MATCH("LT3042", PriceBook!$A:$A, 0)), 0) -> 17382 | AQ12: =Assumptions!$B$6+Assumptions!$B$10*SUM(Tiers!C12:L12) -> 40.365 | AR12: =AN12+AO12+AQ12 -> 2586.7085 | AS12: =AR12*Assumptions!$B$2 -> 594.94296 | AT12: =AR12+AS12 -> 3181.6515 | AU12: =IF(AT12<=2000, CEILING(AT12, 250), CEILING(AT12, 500)) -> 3500
A13: 7x7→16→10 | B13: Yes | C13: 1 | D13: 7 | E13: 7 | F13: 10 | G13: 16 | H13: =IF(B13="Yes", C13*(D13+E13)*IF(G13>0, G13, F13) + IF(G13>0, G13*F13, 0), D13*E13*IF(G13>0, G13, F13) + IF(G13>0, G13*F13, 0)) -> 384 | I13: =H13 -> 384 | J13: 0 | K13: =CEILING(H13/Assumptions!$B$8,1) -> 48 | L13: =F13+G13 -> 26 | M13: =IF(LEFT(A13,4)="€100","ADS1115",IF(LEFT(A13,4)="€250","ADS1115","ADS1263")) -> ADS1263 | N13: =INDEX(PriceBook!$B:$B, MATCH(M13, PriceBook!$A:$A, 0)) -> 19.82 | O13: =IF(LEFT(A13,4)="€100","PICO2",IF(LEFT(A13,4)="€250","PICO2","NUCLEO_U575")) -> NUCLEO_U575 | P13: =INDEX(PriceBook!$B:$B, MATCH(O13, PriceBook!$A:$A, 0)) -> 20.7 | Q13: =L13 -> 26 | R13: =IF(Q13>=100, INDEX(PriceBook!$D:$D, MATCH("OPA140", PriceBook!$A:$A, 0)), IF(Q13>=10, INDEX(PriceBook!$C:$C, MATCH("OPA140", PriceBook!$A:$A, 0)), INDEX(PriceBook!$B:$B, MATCH("OPA140", PriceBook!$A:$A, 0)))) -> 2.8 | S13: =Q13*R13 -> 72.8 | T13: =L13 -> 26 | U13: =INDEX(PriceBook!$B:$B, MATCH("MCP6561", PriceBook!$A:$A, 0)) -> 0.473 | V13: =T13*U13 -> 12.298 | W13: =IF(L13>0,1,0) -> 1 | X13: =INDEX(PriceBook!$B:$B, MATCH("TLV3501", PriceBook!$A:$A, 0)) -> 3.51 | Y13: =W13*X13 -> 3.51 | Z13: =IF(I13>=100, INDEX(PriceBook!$D:$D, MATCH("TPL0102", PriceBook!$A:$A, 0)), IF(I13>=10, INDEX(PriceBook!$C:$C, MATCH("TPL0102", PriceBook!$A:$A, 0)), INDEX(PriceBook!$B:$B, MATCH("TPL0102", PriceBook!$A:$A, 0)))) -> 1.54 | AA13: =I13*Z13 -> 591.36 | AB13: =INDEX(PriceBook!$B:$B, MATCH("TMUX1108", PriceBook!$A:$A, 0)) -> 2.86 | AC13: =J13*AB13 -> 0 | AD13: 4 | AE13: =K13*AD13 -> 192 | AF13: =IF(L13>=5,1,0) -> 1 | AG13: =INDEX(PriceBook!$B:$B, MATCH("ADR4550", PriceBook!$A:$A, 0)) -> 7.49 | AH13: =AF13*AG13 -> 7.49 | AI13: =IF(L13>=5,1,0) -> 1 | AJ13: =INDEX(PriceBook!$B:$B, MATCH("LT3042", PriceBook!$A:$A, 0)) -> 7.82 | AK13: =AI13*AJ13 -> 7.82 | AL13: =N13 -> 19.82 | AM13: =P13 -> 20.7 | AN13: =S13+V13+Y13+AA13+AC13+AE13+AH13+AK13+AL13+AM13 -> 927.798 | AO13: =AN13*Assumptions!$B$2 -> 213.39354 | AP13: =I13*INDEX(PriceBook!$E:$E, MATCH("TPL0102", PriceBook!$A:$A, 0))+J13*INDEX(PriceBook!$E:$E, MATCH("TMUX1108", PriceBook!$A:$A, 0))+K13*INDEX(PriceBook!$E:$E, MATCH("ADG2128", PriceBook!$A:$A, 0))+L13*INDEX(PriceBook!$E:$E, MATCH("OPA140", PriceBook!$A:$A, 0))+L13*INDEX(PriceBook!$E:$E, MATCH("MCP6561", PriceBook!$A:$A, 0))+IF(L13>0, INDEX(PriceBook!$E:$E, MATCH("TLV3501", PriceBook!$A:$A, 0)), 0)+INDEX(PriceBook!$E:$E, MATCH(M13, PriceBook!$A:$A, 0))+IF(L13>=5, INDEX(PriceBook!$E:$E, MATCH("ADR4550", PriceBook!$A:$A, 0)), 0)+IF(L13>=5, INDEX(PriceBook!$E:$E, MATCH("LT3042", PriceBook!$A:$A, 0)), 0) -> 7302 | AQ13: =Assumptions!$B$6+Assumptions!$B$10*SUM(Tiers!C13:L13) -> 34.415 | AR13: =AN13+AO13+AQ13 -> 1175.6065 | AS13: =AR13*Assumptions!$B$2 -> 270.3895 | AT13: =AR13+AS13 -> 1445.996 | AU13: =IF(AT13<=2000, CEILING(AT13, 250), CEILING(AT13, 500)) -> 1500
... A15: 7x7→32→10 | B15: Yes | C15: 1 | D15: 7 | E15: 7 | F15: 10 | G15: 32 | H15: =IF(B15="Yes", C15*(D15+E15)*IF(G15>0, G15, F15) + IF(G15>0, G15*F15, 0), D15*E15*IF(G15>0, G15, F15) + IF(G15>0, G15*F15, 0)) -> 768 | I15: =H15 -> 768 | J15: 0 | K15: =CEILING(H15/Assumptions!$B$8,1) -> 96 | L15: =F15+G15 -> 42 | M15: =IF(LEFT(A15,4)="€100","ADS1115",IF(LEFT(A15,4)="€250","ADS1115","ADS1263")) -> ADS1263 | N15: =INDEX(PriceBook!$B:$B, MATCH(M15, PriceBook!$A:$A, 0)) -> 19.82 | O15: =IF(LEFT(A15,4)="€100","PICO2",IF(LEFT(A15,4)="€250","PICO2","NUCLEO_U575")) -> NUCLEO_U575 | P15: =INDEX(PriceBook!$B:$B, MATCH(O15, PriceBook!$A:$A, 0)) -> 20.7 | Q15: =L15 -> 42 | R15: =IF(Q15>=100, INDEX(PriceBook!$D:$D, MATCH("OPA140", PriceBook!$A:$A, 0)), IF(Q15>=10, INDEX(PriceBook!$C:$C, MATCH("OPA140", PriceBook!$A:$A, 0)), INDEX(PriceBook!$B:$B, MATCH("OPA140", PriceBook!$A:$A, 0)))) -> 2.8 | S15: =Q15*R15 -> 117.6 | T15: =L15 -> 42 | U15: =INDEX(PriceBook!$B:$B, MATCH("MCP6561", PriceBook!$A:$A, 0)) -> 0.473 | V15: =T15*U15 -> 19.866 | W15: =IF(L15>0,1,0) -> 1 | X15: =INDEX(PriceBook!$B:$B, MATCH("TLV3501", PriceBook!$A:$A, 0)) -> 3.51 | Y15: =W15*X15 -> 3.51 | Z15: =IF(I15>=100, INDEX(PriceBook!$D:$D, MATCH("TPL0102", PriceBook!$A:$A, 0)), IF(I15>=10, INDEX(PriceBook!$C:$C, MATCH("TPL0102", PriceBook!$A:$A, 0)), INDEX(PriceBook!$B:$B, MATCH("TPL0102", PriceBook!$A:$A, 0)))) -> 1.54 | AA15: =I15*Z15 -> 1182.72 | AB15: =INDEX(PriceBook!$B:$B, MATCH("TMUX1108", PriceBook!$A:$A, 0)) -> 2.86 | AC15: =J15*AB15 -> 0 | AD15: 4 | AE15: =K15*AD15 -> 384 | AF15: =IF(L15>=5,1,0) -> 1 | AG15: =INDEX(PriceBook!$B:$B, MATCH("ADR4550", PriceBook!$A:$A, 0)) -> 7.49 | AH15: =AF15*AG15 -> 7.49 | AI15: =IF(L15>=5,1,0) -> 1 | AJ15: =INDEX(PriceBook!$B:$B, MATCH("LT3042", PriceBook!$A:$A, 0)) -> 7.82 | AK15: =AI15*AJ15 -> 7.82 | AL15: =N15 -> 19.82 | AM15: =P15 -> 20.7 | AN15: =S15+V15+Y15+AA15+AC15+AE15+AH15+AK15+AL15+AM15 -> 1763.526 | AO15: =AN15*Assumptions!$B$2 -> 405.61098 | AP15: =I15*INDEX(PriceBook!$E:$E, MATCH("TPL0102", PriceBook!$A:$A, 0))+J15*INDEX(PriceBook!$E:$E, MATCH("TMUX1108", PriceBook!$A:$A, 0))+K15*INDEX(PriceBook!$E:$E, MATCH("ADG2128", PriceBook!$A:$A, 0))+L15*INDEX(PriceBook!$E:$E, MATCH("OPA140", PriceBook!$A:$A, 0))+L15*INDEX(PriceBook!$E:$E, MATCH("MCP6561", PriceBook!$A:$A, 0))+IF(L15>0, INDEX(PriceBook!$E:$E, MATCH("TLV3501", PriceBook!$A:$A, 0)), 0)+INDEX(PriceBook!$E:$E, MATCH(M15, PriceBook!$A:$A, 0))+IF(L15>=5, INDEX(PriceBook!$E:$E, MATCH("ADR4550", PriceBook!$A:$A, 0)), 0)+IF(L15>=5, INDEX(PriceBook!$E:$E, MATCH("LT3042", PriceBook!$A:$A, 0)), 0) -> 14422 | AQ15: =Assumptions!$B$6+Assumptions!$B$10*SUM(Tiers!C15:L15) -> 38.655 | AR15: =AN15+AO15+AQ15 -> 2207.792 | AS15: =AR15*Assumptions!$B$2 -> 507.79216 | AT15: =AR15+AS15 -> 2715.5841 | AU15: =IF(AT15<=2000, CEILING(AT15, 250), CEILING(AT15, 500)) -> 3000

Sheet Summary
A1: Tier | B1: Temporal? | C1: Synapses | D1: Digipots | E1: Routing, TMUX | F1: Routing, ADG2128 | G1: Neurons | H1: Active € ex VAT | I1: PCBA € ex VAT | J1: Total € inc VAT | K1: Funding bucket €
A2: =Tiers!A2 -> POC | B2: =Tiers!B2 -> No | C2: =Tiers!H2 -> 1 | D2: =Tiers!I2 -> 1 | E2: =Tiers!J2 -> 0 | F2: =Tiers!K2 -> 1 | G2: =Tiers!L2 -> 1 | H2: =Tiers!AN2 -> 54.713 | I2: =Tiers!AQ2 -> 30.04 | J2: =Tiers!AT2 -> 119.7245 | K2: =Tiers!AU2 -> 250
A3: =Tiers!A3 -> POC | B3: =Tiers!B3 -> Yes | C3: =Tiers!H3 -> 2 | D3: =Tiers!I3 -> 2 | E3: =Tiers!J3 -> 0 | F3: =Tiers!K3 -> 1 | G3: =Tiers!L3 -> 1 | H3: =Tiers!AN3 -> 57.233 | I3: =Tiers!AQ3 -> 30.05 | J3: =Tiers!AT3 -> 123.54931 | K3: =Tiers!AU3 -> 250
A4: =Tiers!A4 -> 3x3→3 | B4: =Tiers!B4 -> No | C4: =Tiers!H4 -> 27 | D4: =Tiers!I4 -> 27 | E4: =Tiers!J4 -> 0 | F4: =Tiers!K4 -> 4 | G4: =Tiers!L4 -> 3 | H4: =Tiers!AN4 -> 123.009 | I4: =Tiers!AQ4 -> 30.355 | J4: =Tiers!AT4 -> 223.43697 | K4: =Tiers!AU4 -> 250
A5: =Tiers!A5 -> 3x3→3 | B5: =Tiers!B5 -> Yes | C5: =Tiers!H5 -> 18 | D5: =Tiers!I5 -> 18 | E5: =Tiers!J5 -> 0 | F5: =Tiers!K5 -> 3 | G5: =Tiers!L5 -> 3 | H5: =Tiers!AN5 -> 102.179 | I5: =Tiers!AQ5 -> 30.26 | J5: =Tiers!AT5 -> 191.80641 | K5: =Tiers!AU5 -> 250
A6: =Tiers!A6 -> 5x5→5 | B6: =Tiers!B6 -> No | C6: =Tiers!H6 -> 125 | D6: =Tiers!I6 -> 125 | E6: =Tiers!J6 -> 0 | F6: =Tiers!K6 -> 16 | G6: =Tiers!L6 -> 5 | H6: =Tiers!AN6 -> 336.655 | I6: =Tiers!AQ6 -> 31.435 | J6: =Tiers!AT6 -> 547.9904 | K6: =Tiers!AU6 -> 750
A7: =Tiers!A7 -> 5x5→5 | B7: =Tiers!B7 -> Yes | C7: =Tiers!H7 -> 50 | D7: =Tiers!I7 -> 50 | E7: =Tiers!J7 -> 0 | F7: =Tiers!K7 -> 7 | G7: =Tiers!L7 -> 5 | H7: =Tiers!AN7 -> 201.655 | I7: =Tiers!AQ7 -> 30.64 | J7: =Tiers!AT7 -> 342.77105 | K7: =Tiers!AU7 -> 500
A8: =Tiers!A8 -> 7x7→5 | B8: =Tiers!B8 -> No | C8: =Tiers!H8 -> 245 | D8: =Tiers!I8 -> 245 | E8: =Tiers!J8 -> 0 | F8: =Tiers!K8 -> 31 | G8: =Tiers!L8 -> 5 | H8: =Tiers!AN8 -> 581.455 | I8: =Tiers!AQ8 -> 32.73 | J8: =Tiers!AT8 -> 919.94117 | K8: =Tiers!AU8 -> 1000
A9: =Tiers!A9 -> 7x7→5 | B9: =Tiers!B9 -> Yes | C9: =Tiers!H9 -> 70 | D9: =Tiers!I9 -> 70 | E9: =Tiers!J9 -> 0 | F9: =Tiers!K9 -> 9 | G9: =Tiers!L9 -> 5 | H9: =Tiers!AN9 -> 247.055 | I9: =Tiers!AQ9 -> 30.87 | J9: =Tiers!AT9 -> 411.73961 | K9: =Tiers!AU9 -> 500
A10: =Tiers!A10 -> 7x7→10 | B10: =Tiers!B10 -> No | C10: =Tiers!H10 -> 490 | D10: =Tiers!I10 -> 490 | E10: =Tiers!J10 -> 0 | F10: =Tiers!K10 -> 62 | G10: =Tiers!L10 -> 10 | H10: =Tiers!AN10 -> 1094.67 | I10: =Tiers!AQ10 -> 35.385 | J10: =Tiers!AT10 -> 1699.6498 | K10: =Tiers!AU10 -> 1750
A11: =Tiers!A11 -> 7x7→10 | B11: =Tiers!B11 -> Yes | C11: =Tiers!H11 -> 140 | D11: =Tiers!I11 -> 140 | E11: =Tiers!J11 -> 0 | F11: =Tiers!K11 -> 18 | G11: =Tiers!L11 -> 10 | H11: =Tiers!AN11 -> 379.67 | I11: =Tiers!AQ11 -> 31.665 | J11: =Tiers!AT11 -> 613.35069 | K11: =Tiers!AU11 -> 750
A12: =Tiers!A12 -> 7x7→16→10 | B12: =Tiers!B12 -> No | C12: =Tiers!H12 -> 944 | D12: =Tiers!I12 -> 944 | E12: =Tiers!J12 -> 0 | F12: =Tiers!K12 -> 118 | G12: =Tiers!L12 -> 26 | H12: =Tiers!AN12 -> 2070.198 | I12: =Tiers!AQ12 -> 40.365 | J12: =Tiers!AT12 -> 3181.6515 | K12: =Tiers!AU12 -> 3500
A13: =Tiers!A13 -> 7x7→16→10 | B13: =Tiers!B13 -> Yes | C13: =Tiers!H13 -> 384 | D13: =Tiers!I13 -> 384 | E13: =Tiers!J13 -> 0 | F13: =Tiers!K13 -> 48 | G13: =Tiers!L13 -> 26 | H13: =Tiers!AN13 -> 927.798 | I13: =Tiers!AQ13 -> 34.415 | J13: =Tiers!AT13 -> 1445.996 | K13: =Tiers!AU13 -> 1500
... A15: =Tiers!A15 -> 7x7→32→10 | B15: =Tiers!B15 -> Yes | C15: =Tiers!H15 -> 768 | D15: =Tiers!I15 -> 768 | E15: =Tiers!J15 -> 0 | F15: =Tiers!K15 -> 96 | G15: =Tiers!L15 -> 42 | H15: =Tiers!AN15 -> 1763.526 | I15: =Tiers!AQ15 -> 38.655 | J15: =Tiers!AT15 -> 2715.5841 | K15: =Tiers!AU15 -> 3000
